docal/__init__.py
docal/__main__.py
docal/calculation.py
docal/lsp.py
docal/parsing.py
docal/processing.py
docal/document/__init__.py
docal/document/latex.py
docal/document/word.docx
docal/document/word.py
docal/parsers/dcl.py
docal/parsers/excel.py
docal-4.2.1.dist-info/METADATA
docal-4.2.1.dist-info/WHEEL
docal-4.2.1.dist-info/entry_points.txt
docal-4.2.1.dist-info/top_level.txt
docal-4.2.1.dist-info/RECORD
