Metadata-Version: 2.4
Name: docal
Version: 4.2.1
Summary: Inject calculations into Word and LaTeX documents with ease!
Author-email: Kidus Adugna <kidusadugna@gmail.com>
License: MIT
Project-URL: Homepage, https://github.com/K1DV5/docal
Project-URL: Issues, https://github.com/K1DV5/docal/issues
Keywords: docal,math,latex,word,engineering,equation,calculations,mathcad,scientific-reports
Classifier: Development Status :: 5 - Production/Stable
Classifier: Intended Audience :: Developers
Classifier: Intended Audience :: End Users/Desktop
Classifier: License :: OSI Approved :: MIT License
Classifier: Natural Language :: English
Classifier: Programming Language :: Python :: 3
Requires-Python: >=3.13
Provides-Extra: dev
Requires-Dist: pytest; extra == "dev"
Provides-Extra: lsp
Requires-Dist: pygls; extra == "lsp"
